MANIFEST.in
README.rst
setup.cfg
setup.py
collective/__init__.py
collective.login_monitor.egg-info/PKG-INFO
collective.login_monitor.egg-info/SOURCES.txt
collective.login_monitor.egg-info/dependency_links.txt
collective.login_monitor.egg-info/entry_points.txt
collective.login_monitor.egg-info/namespace_packages.txt
collective.login_monitor.egg-info/not-zip-safe
collective.login_monitor.egg-info/requires.txt
collective.login_monitor.egg-info/top_level.txt
collective/login_monitor/__init__.py
collective/login_monitor/configure.zcml
collective/login_monitor/event.py
collective/login_monitor/interfaces.py
collective/login_monitor/models.py
collective/login_monitor/prepare_model.py
collective/login_monitor/upgrades.py
collective/login_monitor/Extensions/install.py
collective/login_monitor/browser/__init__.py
collective/login_monitor/browser/configure.zcml
collective/login_monitor/browser/login_logger_macros.pt
collective/login_monitor/browser/search.pt
collective/login_monitor/browser/view.py
collective/login_monitor/locales/collective.login_monitor-manual.pot
collective/login_monitor/locales/collective.login_monitor.pot
collective/login_monitor/locales/rebuildPo.sh
collective/login_monitor/locales/it/LC_MESSAGES/collective.login_monitor.po
collective/login_monitor/profiles/default/browserlayer.xml
collective/login_monitor/profiles/default/controlpanel.xml
collective/login_monitor/profiles/default/metadata.xml
collective/login_monitor/profiles/default/registry.xml
collective/login_monitor/profiles/default/rolemap.xml
collective/login_monitor/profiles/uninstall/browserlayer.xml
collective/login_monitor/profiles/uninstall/controlpanel.xml
docs/HISTORY.rst
docs/INSTALL.txt
docs/LICENSE.GPL
docs/LICENSE.txt